auraflow_client
tests
