Metadata-Version: 2.1
Name: auraflow-client
Version: 0.1.3
Summary: An auraflow_client library for interacting with the AuraFlow API
Home-page: UNKNOWN
Author: Usama Ali
Author-email: usamaali012@gmail.com
License: UNKNOWN
Platform: UNKNOWN
Classifier: Development Status :: 3 - Alpha
Classifier: Intended Audience :: Developers
Classifier: Natural Language :: English
Classifier: Programming Language :: Python :: 3
Classifier: Programming Language :: Python :: 3.8
Classifier: Topic :: Software Development :: Libraries
Classifier: License :: OSI Approved :: MIT License
Requires-Python: >=3.8
License-File: LICENSE.md
